lostify/__init__.py
lostify/client.py
lostify-1.0.8.dist-info/METADATA
lostify-1.0.8.dist-info/WHEEL
lostify-1.0.8.dist-info/top_level.txt
lostify-1.0.8.dist-info/RECORD
