Metadata-Version: 2.1
Name: lostify
Version: 1.0.8
Summary: A Spotify API wrapper dedicated to people with a brain
Home-page: https://wock.club
Author: .()#1030
Author-email: UNKNOWN
License: UNKNOWN
Download-URL: https://github.com/qcki/lostify/archive/refs/tags/Beta.tar.gz
Platform: UNKNOWN
Requires-Dist: aiohttp (<3.9.0,>=3.6.0)
